README.md
pyproject.toml
setup.py
m_kafka_sdk_v2.egg-info/PKG-INFO
m_kafka_sdk_v2.egg-info/SOURCES.txt
m_kafka_sdk_v2.egg-info/dependency_links.txt
m_kafka_sdk_v2.egg-info/namespace_packages.txt
m_kafka_sdk_v2.egg-info/requires.txt
m_kafka_sdk_v2.egg-info/top_level.txt
mobio/libs/__init__.py
mobio/libs/kafka_lib/__init__.py
mobio/libs/kafka_lib/helpers/__init__.py
mobio/libs/kafka_lib/helpers/batch_consumer_manager.py
mobio/libs/kafka_lib/helpers/ensure_kafka_topic.py
mobio/libs/kafka_lib/helpers/kafka_consumer_manager.py
mobio/libs/kafka_lib/helpers/kafka_producer_manager.py
mobio/libs/kafka_lib/helpers/redisbloom_client.py
mobio/libs/kafka_lib/models/__init__.py
mobio/libs/kafka_lib/models/mongo/__init__.py
mobio/libs/kafka_lib/models/mongo/base_model.py
mobio/libs/kafka_lib/models/mongo/requeue_consumer_model.py
test/test_consumer.py
test/test_singleton.py