Metadata-Version: 2.1
Name: m-kafka-sdk-v2
Version: 1.0.2
Summary: Mobio Kafka SDK
Home-page: https://github.com/mobiovn
Author: MOBIO
Author-email: contact@mobio.vn
License: MIT
Project-URL: Source, https://github.com/mobiovn
Keywords: mobio,kafka,m-kafka
Classifier: Development Status :: 3 - Alpha
Classifier: Intended Audience :: Developers
Classifier: Topic :: Software Development :: Build Tools
Classifier: License :: OSI Approved :: MIT License
Classifier: Programming Language :: Python :: 3
Classifier: Programming Language :: Python :: 3.6
Classifier: Programming Language :: Python :: 3.7
Classifier: Programming Language :: Python :: 3.8
Classifier: Programming Language :: Python :: 3.9
Classifier: Programming Language :: Python :: 3 :: Only
Requires-Python: >=3
Requires-Dist: requests>=2.25.1
Requires-Dist: confluent-kafka>=1.7.0
Requires-Dist: redisbloom<=0.4.0
Requires-Dist: m-singleton>=0.3
